egregore/__init__.py
egregore/analytics/__init__.py
egregore/analytics/context_explorer/__init__.py
egregore/analytics/context_explorer/explorer.py
egregore/analytics/context_viewer/__init__.py
egregore/analytics/context_viewer/formatters.py
egregore/analytics/context_viewer/provider_renderer.py
egregore/analytics/context_viewer/rich_text_renderer.py
egregore/analytics/context_viewer/text_renderer.py
egregore/analytics/context_viewer/tree_renderer.py
egregore/analytics/context_viewer/utils.py
egregore/analytics/context_viewer/viewer.py
egregore/analytics/context_viewer/xml_renderer.py
egregore/analytics/step_simulator/__init__.py
egregore/core/agent/__init__.py
egregore/core/agent/agent_context.py
egregore/core/agent/base/__init__.py
egregore/core/agent/base/config.py
egregore/core/agent/base/controller.py
egregore/core/agent/base/provider_info.py
egregore/core/agent/base/streaming_ops.py
egregore/core/agent/base/task_loop_ops.py
egregore/core/agent/base/token_operations.py
egregore/core/agent/events/__init__.py
egregore/core/agent/events/agent.py
egregore/core/agent/events/context.py
egregore/core/agent/events/event_types.py
egregore/core/agent/events/hook_mapping.py
egregore/core/agent/events/scaffold.py
egregore/core/agent/events/stream.py
egregore/core/agent/events/stream_controller.py
egregore/core/agent/events/tool.py
egregore/core/agent/failed_streams.py
egregore/core/agent/hooks/__init__.py
egregore/core/agent/hooks/accessors.py
egregore/core/agent/hooks/execution.py
egregore/core/agent/hooks/execution_contexts.py
egregore/core/agent/hooks/subscribe.py
egregore/core/agent/hooks_accessor.py
egregore/core/agent/message_scheduler.py
egregore/core/agent/state.py
egregore/core/agent/streaming_orchestrator.py
egregore/core/agent/tool_task_loop.py
egregore/core/agent/utils.py
egregore/core/context_management/__init__.py
egregore/core/context_management/context_tree.py
egregore/core/context_management/history/__init__.py
egregore-0.1.4a0.dist-info/METADATA
egregore-0.1.4a0.dist-info/WHEEL
egregore-0.1.4a0.dist-info/entry_points.txt
egregore-0.1.4a0.dist-info/RECORD
