Metadata-Version: 2.3
Name: egregore
Version: 0.1.4a0
Summary: Tools for creating llm applications
Author: Earl Dennison Tan
Requires-Python: >=3.11,<3.13
Classifier: Programming Language :: Python :: 3
Classifier: Programming Language :: Python :: 3.11
Classifier: Programming Language :: Python :: 3.12
Requires-Dist: aiohttp (>=3.11.0,<4.0.0)
Requires-Dist: any-llm-sdk (>=0.20.3,<0.21.0)
Requires-Dist: jinja2 (>=3.1.6,<4.0.0)
Requires-Dist: lark (>=1.2.2,<2.0.0)
Requires-Dist: platformdirs (>=4.0.0,<5.0.0)
Requires-Dist: pydantic (>=2.7.1,<3.0.0)
Requires-Dist: python-dotenv (>=1.0.0,<2.0.0)
Requires-Dist: requests (>=2.32.3,<3.0.0)
Requires-Dist: rich (>=13.9.4,<14.0.0)
Requires-Dist: tiktoken (>=0.7.0,<0.8.0)
Requires-Dist: tokenizers (>=0.21.1,<0.22.0)
